testcodemyyy/__init__.py
testcodemyyy/core.py
testcodemyyy-0.1.0.dist-info/licenses/LICENSE
testcodemyyy-0.1.0.dist-info/METADATA
testcodemyyy-0.1.0.dist-info/WHEEL
testcodemyyy-0.1.0.dist-info/top_level.txt
testcodemyyy-0.1.0.dist-info/RECORD
