Metadata-Version: 2.4
Name: testcodemyyy
Version: 0.1.0
Summary: A cool Python library with awesome features 🐍✨
Author: MohammadReza
Author-email: narnama.room@gmail.com
Classifier: Programming Language :: Python :: 3
Classifier: License :: OSI Approved :: MIT License
Classifier: Operating System :: OS Independent
Requires-Python: >=3.6
License-File: LICENSE
Dynamic: author
Dynamic: author-email
Dynamic: classifier
Dynamic: description
Dynamic: description-content-type
Dynamic: license-file
Dynamic: requires-python
Dynamic: summary
